ansiblerunner/__init__.py
ansiblerunner/callback.py
ansiblerunner/exceptions.py
ansiblerunner/inventory.py
ansiblerunner/option.py
ansiblerunner/runner.py
ansiblerunnerapi-0.0.2.dist-info/METADATA
ansiblerunnerapi-0.0.2.dist-info/WHEEL
ansiblerunnerapi-0.0.2.dist-info/top_level.txt
ansiblerunnerapi-0.0.2.dist-info/RECORD
