Metadata-Version: 2.1
Name: ansiblerunnerapi
Version: 0.0.2
Summary: Ansible Runner API package
Home-page: https://github.com/Maliaotw/ansiblerunner.git
Author: Maliao
Author-email: maliaotw@gmail.com
License: UNKNOWN
Platform: UNKNOWN
Classifier: Programming Language :: Python :: 3
Classifier: License :: OSI Approved :: MIT License
Classifier: Operating System :: OS Independent
Requires-Python: >=3.6
Requires-Dist: ansible (==2.8.8)
